{
    "AAVE/AUD": "AAVEZAUD",
    "AAVE/ETH": "AAVEXETH",
    "AAVE/EUR": "AAVEZEUR",
    "AAVE/GBP": "AAVEZGBP",
    "AAVE/USD": "AAVEZUSD",
    "AAVE/XBT": "AAVEXXBT",
    "ADA/AUD": "ADAZAUD",
    "ADA/ETH": "ADAXETH",
    "ADA/EUR": "ADAZEUR",
    "ADA/GBP": "ADAZGBP",
    "ADA/USD": "ADAZUSD",
    "ADA/USDT": "ADAUSDT",
    "ADA/XBT": "ADAXXBT",
    "ALGO/ETH": "ALGOXETH",
    "ALGO/EUR": "ALGOZEUR",
    "ALGO/GBP": "ALGOZGBP",
    "ALGO/USD": "ALGOZUSD",
    "ALGO/XBT": "ALGOXXBT",
    "ANT/ETH": "ANTXETH",
    "ANT/EUR": "ANTZEUR",
    "ANT/USD": "ANTZUSD",
    "ANT/XBT": "ANTXXBT",
    "ATOM/AUD": "ATOMZAUD",
    "ATOM/ETH": "ATOMXETH",
    "ATOM/EUR": "ATOMZEUR",
    "ATOM/GBP": "ATOMZGBP",
    "ATOM/USD": "ATOMZUSD",
    "ATOM/XBT": "ATOMXXBT",
    "AUD/JPY": "ZAUDZJPY",
    "AUD/USD": "ZAUDZUSD",
    "BAL/ETH": "BALXETH",
    "BAL/EUR": "BALZEUR",
    "BAL/USD": "BALZUSD",
    "BAL/XBT": "BALXXBT",
    "BAT/ETH": "BATXETH",
    "BAT/EUR": "BATZEUR",
    "BAT/USD": "BATZUSD",
    "BAT/XBT": "BATXXBT",
    "BCH/AUD": "BCHZAUD",
    "BCH/ETH": "BCHXETH",
    "BCH/EUR": "BCHZEUR",
    "BCH/GBP": "BCHZGBP",
    "BCH/JPY": "BCHZJPY",
    "BCH/USD": "BCHZUSD",
    "BCH/USDT": "BCHUSDT",
    "BCH/XBT": "BCHXXBT",
    "COMP/ETH": "COMPXETH",
    "COMP/EUR": "COMPZEUR",
    "COMP/USD": "COMPZUSD",
    "COMP/XBT": "COMPXXBT",
    "CRV/ETH": "CRVXETH",
    "CRV/EUR": "CRVZEUR",
    "CRV/USD": "CRVZUSD",
    "CRV/XBT": "CRVXXBT",
    "DAI/EUR": "DAIZEUR",
    "DAI/USD": "DAIZUSD",
    "DAI/USDT": "DAIUSDT",
    "DASH/EUR": "DASHZEUR",
    "DASH/USD": "DASHZUSD",
    "DASH/XBT": "DASHXXBT",
    "DOT/AUD": "DOTZAUD",
    "DOT/ETH": "DOTXETH",
    "DOT/EUR": "DOTZEUR",
    "DOT/GBP": "DOTZGBP",
    "DOT/USD": "DOTZUSD",
    "DOT/USDT": "DOTUSDT",
    "DOT/XBT": "DOTXXBT",
    "EOS/ETH": "EOSXETH",
    "EOS/EUR": "EOSZEUR",
    "EOS/USD": "EOSZUSD",
    "EOS/USDT": "EOSUSDT",
    "EOS/XBT": "EOSXXBT",
    "ETH2.S/ETH": "ETH2.SXETH",
    "ETH/AUD": "XETHZAUD",
    "ETH/CHF": "XETHCHF",
    "ETH/DAI": "XETHDAI",
    "ETH/USDC": "XETHUSDC",
    "ETH/USDT": "XETHUSDT",
    "EUR/AUD": "ZEURZAUD",
    "EUR/CAD": "ZEURZCAD",
    "EUR/CHF": "ZEURCHF",
    "EUR/GBP": "ZEURZGBP",
    "EUR/JPY": "ZEURZJPY",
    "EWT/EUR": "EWTZEUR",
    "EWT/GBP": "EWTZGBP",
    "EWT/USD": "EWTZUSD",
    "EWT/XBT": "EWTXXBT",
    "FIL/AUD": "FILZAUD",
    "FIL/ETH": "FILXETH",
    "FIL/EUR": "FILZEUR",
    "FIL/GBP": "FILZGBP",
    "FIL/USD": "FILZUSD",
    "FIL/XBT": "FILXXBT",
    "FLOW/ETH": "FLOWXETH",
    "FLOW/EUR": "FLOWZEUR",
    "FLOW/GBP": "FLOWZGBP",
    "FLOW/USD": "FLOWZUSD",
    "FLOW/XBT": "FLOWXXBT",
    "GNO/ETH": "GNOXETH",
    "GNO/EUR": "GNOZEUR",
    "GNO/USD": "GNOZUSD",
    "GNO/XBT": "GNOXXBT",
    "GRT/AUD": "GRTZAUD",
    "GRT/ETH": "GRTXETH",
    "GRT/EUR": "GRTZEUR",
    "GRT/GBP": "GRTZGBP",
    "GRT/USD": "GRTZUSD",
    "GRT/XBT": "GRTXXBT",
    "ICX/ETH": "ICXXETH",
    "ICX/EUR": "ICXZEUR",
    "ICX/USD": "ICXZUSD",
    "ICX/XBT": "ICXXXBT",
    "KAVA/ETH": "KAVAXETH",
    "KAVA/EUR": "KAVAZEUR",
    "KAVA/USD": "KAVAZUSD",
    "KAVA/XBT": "KAVAXXBT",
    "KEEP/ETH": "KEEPXETH",
    "KEEP/EUR": "KEEPZEUR",
    "KEEP/USD": "KEEPZUSD",
    "KEEP/XBT": "KEEPXXBT",
    "KNC/ETH": "KNCXETH",
    "KNC/EUR": "KNCZEUR",
    "KNC/USD": "KNCZUSD",
    "KNC/XBT": "KNCXXBT",
    "KSM/AUD": "KSMZAUD",
    "KSM/DOT": "KSMDOT",
    "KSM/ETH": "KSMXETH",
    "KSM/EUR": "KSMZEUR",
    "KSM/GBP": "KSMZGBP",
    "KSM/USD": "KSMZUSD",
    "KSM/XBT": "KSMXXBT",
    "LINK/AUD": "LINKZAUD",
    "LINK/ETH": "LINKXETH",
    "LINK/EUR": "LINKZEUR",
    "LINK/GBP": "LINKZGBP",
    "LINK/USD": "LINKZUSD",
    "LINK/USDT": "LINKUSDT",
    "LINK/XBT": "LINKXXBT",
    "LSK/ETH": "LSKXETH",
    "LSK/EUR": "LSKZEUR",
    "LSK/USD": "LSKZUSD",
    "LSK/XBT": "LSKXXBT",
    "LTC/AUD": "XLTCZAUD",
    "LTC/ETH": "XLTCXETH",
    "LTC/GBP": "XLTCZGBP",
    "LTC/USDT": "XLTCUSDT",
    "MANA/ETH": "MANAXETH",
    "MANA/EUR": "MANAZEUR",
    "MANA/USD": "MANAZUSD",
    "MANA/XBT": "MANAXXBT",
    "NANO/ETH": "NANOXETH",
    "NANO/EUR": "NANOZEUR",
    "NANO/USD": "NANOZUSD",
    "NANO/XBT": "NANOXXBT",
    "OCEAN/EUR": "OCEANZEUR",
    "OCEAN/GBP": "OCEANZGBP",
    "OCEAN/USD": "OCEANZUSD",
    "OCEAN/XBT": "OCEANXXBT",
    "OMG/ETH": "OMGXETH",
    "OMG/EUR": "OMGZEUR",
    "OMG/USD": "OMGZUSD",
    "OMG/XBT": "OMGXXBT",
    "OXT/ETH": "OXTXETH",
    "OXT/EUR": "OXTZEUR",
    "OXT/USD": "OXTZUSD",
    "OXT/XBT": "OXTXXBT",
    "PAXG/ETH": "PAXGXETH",
    "PAXG/EUR": "PAXGZEUR",
    "PAXG/USD": "PAXGZUSD",
    "PAXG/XBT": "PAXGXXBT",
    "QTUM/ETH": "QTUMXETH",
    "QTUM/EUR": "QTUMZEUR",
    "QTUM/USD": "QTUMZUSD",
    "QTUM/XBT": "QTUMXXBT",
    "REPV2/ETH": "REPV2XETH",
    "REPV2/EUR": "REPV2ZEUR",
    "REPV2/USD": "REPV2ZUSD",
    "REPV2/XBT": "REPV2XXBT",
    "SC/ETH": "SCXETH",
    "SC/EUR": "SCZEUR",
    "SC/USD": "SCZUSD",
    "SC/XBT": "SCXXBT",
    "SNX/AUD": "SNXZAUD",
    "SNX/ETH": "SNXXETH",
    "SNX/EUR": "SNXZEUR",
    "SNX/GBP": "SNXZGBP",
    "SNX/USD": "SNXZUSD",
    "SNX/XBT": "SNXXXBT",
    "STORJ/ETH": "STORJXETH",
    "STORJ/EUR": "STORJZEUR",
    "STORJ/USD": "STORJZUSD",
    "STORJ/XBT": "STORJXXBT",
    "TBTC/ETH": "TBTCXETH",
    "TBTC/EUR": "TBTCZEUR",
    "TBTC/USD": "TBTCZUSD",
    "TBTC/XBT": "TBTCXXBT",
    "TRX/ETH": "TRXXETH",
    "TRX/EUR": "TRXZEUR",
    "TRX/USD": "TRXZUSD",
    "TRX/XBT": "TRXXXBT",
    "UNI/ETH": "UNIXETH",
    "UNI/EUR": "UNIZEUR",
    "UNI/USD": "UNIZUSD",
    "UNI/XBT": "UNIXXBT",
    "USDC/AUD": "USDCZAUD",
    "USDC/EUR": "USDCZEUR",
    "USDC/GBP": "USDCZGBP",
    "USD/CHF": "ZUSDCHF",
    "USDC/USD": "USDCZUSD",
    "USDC/USDT": "USDCUSDT",
    "USDT/AUD": "USDTZAUD",
    "USDT/CAD": "USDTZCAD",
    "USDT/CHF": "USDTCHF",
    "USDT/EUR": "USDTZEUR",
    "USDT/GBP": "USDTZGBP",
    "USDT/JPY": "USDTZJPY",
    "USDT/USD": "USDTZUSD",
    "WAVES/ETH": "WAVESXETH",
    "WAVES/EUR": "WAVESZEUR",
    "WAVES/USD": "WAVESZUSD",
    "WAVES/XBT": "WAVESXXBT",
    "XBT/AUD": "XXBTZAUD",
    "XBT/CHF": "XXBTCHF",
    "XBT/DAI": "XXBTDAI",
    "XBT/USDC": "XXBTUSDC",
    "XBT/USDT": "XXBTUSDT",
    "XDG/EUR": "XXDGZEUR",
    "XDG/USD": "XXDGZUSD",
    "XDG/USDT": "XXDGUSDT",
    "ETC/ETH": "XETCXETH",
    "ETC/XBT": "XETCXXBT",
    "ETC/EUR": "XETCZEUR",
    "ETC/USD": "XETCZUSD",
    "ETH/XBT": "XETHXXBT",
    "undefined": "XXBTZUSD",
    "ETH/CAD": "XETHZCAD",
    "ETH/EUR": "XETHZEUR",
    "ETH/GBP": "XETHZGBP",
    "ETH/JPY": "XETHZJPY",
    "ETH/USD": "XETHZUSD",
    "LTC/XBT": "XLTCXXBT",
    "LTC/EUR": "XLTCZEUR",
    "LTC/JPY": "XLTCZJPY",
    "LTC/USD": "XLTCZUSD",
    "MLN/ETH": "XMLNXETH",
    "MLN/XBT": "XMLNXXBT",
    "MLN/EUR": "XMLNZEUR",
    "MLN/USD": "XMLNZUSD",
    "REP/ETH": "XREPXETH",
    "REP/XBT": "XREPXXBT",
    "REP/EUR": "XREPZEUR",
    "REP/USD": "XREPZUSD",
    "XRP/AUD": "XXRPZAUD",
    "XRP/ETH": "XXRPXETH",
    "XRP/GBP": "XXRPZGBP",
    "XRP/USDT": "XXRPUSDT",
    "XTZ/AUD": "XTZZAUD",
    "XTZ/ETH": "XTZXETH",
    "XTZ/EUR": "XTZZEUR",
    "XTZ/GBP": "XTZZGBP",
    "XTZ/USD": "XTZZUSD",
    "XTZ/XBT": "XTZXXBT",
    "XBT/CAD": "XXBTZCAD",
    "XBT/EUR": "XXBTZEUR",
    "XBT/GBP": "XXBTZGBP",
    "XBT/JPY": "XXBTZJPY",
    "XBT/USD": "XXBTZUSD",
    "XDG/XBT": "XXDGXXBT",
    "XLM/XBT": "XXLMXXBT",
    "XLM/AUD": "XXLMZAUD",
    "XLM/EUR": "XXLMZEUR",
    "XLM/GBP": "XXLMZGBP",
    "XLM/USD": "XXLMZUSD",
    "XMR/XBT": "XXMRXXBT",
    "XMR/EUR": "XXMRZEUR",
    "XMR/USD": "XXMRZUSD",
    "XRP/XBT": "XXRPXXBT",
    "XRP/CAD": "XXRPZCAD",
    "XRP/EUR": "XXRPZEUR",
    "XRP/JPY": "XXRPZJPY",
    "XRP/USD": "XXRPZUSD",
    "ZEC/XBT": "XZECXXBT",
    "ZEC/EUR": "XZECZEUR",
    "ZEC/USD": "XZECZUSD",
    "YFI/AUD": "YFIZAUD",
    "YFI/ETH": "YFIXETH",
    "YFI/EUR": "YFIZEUR",
    "YFI/GBP": "YFIZGBP",
    "YFI/USD": "YFIZUSD",
    "YFI/XBT": "YFIXXBT",
    "EUR/USD": "ZEURZUSD",
    "GBP/USD": "ZGBPZUSD",
    "USD/CAD": "ZUSDZCAD",
    "USD/JPY": "ZUSDZJPY"
}